{
    "function_tdplyr_name": "td_knn_mle",
    "function_r_name": "aa.knn",
    "function_alias_name": "KNN",
    "input_tables": [
        {
            "rName": "train",
            "name": [
                "TrainingTable",
                "TrainingData"
            ],
            "useInR": true,
            "rOrderNum": 1
        },
        {
            "rName": "test",
            "name": [
                "TestTable",
                "TestData"
            ],
            "useInR": true,
            "rOrderNum": 2
        }
    ],
    "function_name": "KNN",
    "function_tdml_name": "KNN",
    "output_tables": [{
        "rName": "output.table",
        "name": ["OutputTable"],
        "useInR": true,
        "rOrderNum": 100
    }],
    "argument_clauses": [
        {
            "datatype": "COLUMN_NAMES",
            "rName": "response.column",
            "name": ["ResponseColumn"],
            "useInR": true,
            "rOrderNum": 4
        },
        {
            "datatype": "COLUMN_NAMES",
            "rName": "id.column",
            "name": ["IdColumn"],
            "useInR": true,
            "rOrderNum": 5
        },
        {
            "allowsLists": true,
            "datatype": "COLUMN_NAMES",
            "rName": "distance.features",
            "name": ["DistanceFeatures"],
            "useInR": true,
            "rOrderNum": 6
        },
        {
            "datatype": "COLUMN_NAMES",
            "rName": "partition.key",
            "name": ["PartitionColumn"],
            "useInR": true,
            "rOrderNum": 11
        },
        {
            "allowsLists": true,
            "datatype": "COLUMN_NAMES",
            "rName": "accumulate",
            "name": ["Accumulate"],
            "useInR": true,
            "rOrderNum": 12
        },
        {
            "datatype": "INTEGER",
            "rName": "k",
            "name": ["K"],
            "useInR": true,
            "rOrderNum": 3
        },
        {
            "datatype": "INTEGER",
            "rName": "parblock.size",
            "name": ["PartitionBlockSize"],
            "useInR": true,
            "rOrderNum": 10
        },
        {
            "datatype": "INTEGER",
            "rName": "test.block.size",
            "name": ["TestBlockSize"],
            "useInR": true,
            "rOrderNum": 14
        },
        {
            "datatype": "BOOLEAN",
            "rName": "force.mapreduce",
            "name": ["ForceMapreduce"],
            "useInR": true,
            "rOrderNum": 9
        },
        {
            "allowsLists": true,
            "datatype": "STRING",
            "rName": "customized.distance",
            "name": ["CustomizedDistance"],
            "useInR": true,
            "rOrderNum": 8
        },
        {
            "datatype": "DOUBLE",
            "rName": "voting.weight",
            "name": ["VotingWeight"],
            "useInR": true,
            "rOrderNum": 7
        },
        {
            "datatype": "BOOLEAN",
            "rName": "output.prob",
            "name": ["OutputProb"],
            "useInR": true,
            "rOrderNum": 13
        },
        {
            "allowsLists": true,
            "datatype": "STRING",
            "rName": "output.responses",
            "name": ["Responses"],
            "useInR": true,
            "rOrderNum": 15
        },
        {
            "allowsLists": true,
            "datatype": "COLUMN_NAMES",
            "rName": "sequence.column",
            "name": [
                "SequenceInputBy",
                "UniqueId"
            ],
            "useInR": true,
            "rOrderNum": 50
        }
    ]
}
